lillib/__init__.py
lillib/json_filetree.py
lillib/units.py
lillib-0.2.0.dist-info/licenses/LICENSE
lillib-0.2.0.dist-info/METADATA
lillib-0.2.0.dist-info/WHEEL
lillib-0.2.0.dist-info/top_level.txt
lillib-0.2.0.dist-info/RECORD
