Metadata-Version: 2.4
Name: lillib
Version: 0.2.0
Summary: A small collection of utility functions
Author-email: Lilly <ghostoverflow256@gmail.com>
License-Expression: AGPL-3.0-or-later
Project-URL: Homepage, https://github.com/GhostDog98/lillib
Keywords: utilities,formatting,human-readable
Classifier: Programming Language :: Python :: 3
Classifier: Operating System :: OS Independent
Classifier: Development Status :: 3 - Alpha
Classifier: Topic :: Utilities
Requires-Python: >=3.6
License-File: LICENSE
Dynamic: license-file
